attotimebuilder/__init__.py
attotimebuilder/version.py
attotimebuilder/tests/__init__.py
attotimebuilder/tests/test_init.py
attotimebuilder-0.4.2.dist-info/licenses/LICENSE
attotimebuilder-0.4.2.dist-info/METADATA
attotimebuilder-0.4.2.dist-info/WHEEL
attotimebuilder-0.4.2.dist-info/top_level.txt
attotimebuilder-0.4.2.dist-info/RECORD
